{"width":10,"height":10,"pixels":["#C3EA99","#C3EA99","#C3EA99","#C3EA99","#C3EA99","#C3EA99","#C3EA99","#F4F101","#F4F101","#C3EA99","#C3EA99","#C3EA99","#C3EA99","#C3EA99","#F4F101","#F4F101","#F4F101","#EDD400","#EDD400","#F4F101","#C3EA99","#C3EA99","#C3EA99","#F4F101","#F4F101","#F4F101","#DBAF01","#EDD400","#F4F101","#EDD400","#C3EA99","#C3EA99","#F4F101","#F4F101","#F4F101","#DBAF01","#EDD400","#DBAF01","#F4F101","#EDD400","#C3EA99","#F4F101","#F4F101","#F4F101","#DBAF01","#EDD400","#EDD400","#DBAF01","#F4F101","#EDD400","#C3EA99","#F4F101","#F4F101","#EDD400","#C3EA99","#EDD400","#DBAF01","#F4F101","#F4F101","#EDD400","#F4F101","#F4F101","#EDD400","#C3EA99","#EDD400","#EDD400","#DBAF01","#F4F101","#F4F101","#EDD400","#F4F101","#F4F101","#EDD400","#C3EA99","#EDD400","#EDD400","#DBAF01","#F4F101","#EDD400","#EDD400","#F4F101","#EDD400","#C3EA99","#C3EA99","#EDD400","#DBAF01","#DBAF01","#F4F101","#EDD400","#C3EA99","#F4F101","#EDD400","#C3EA99","#EDD400","#EDD400","#DBAF01","#C3EA99","#F4F101","#EDD400","#C3EA99"],"backgroundcolor":["#C3EA99"],"g_width":"10","g_height":"10"}